{
  "glyphs": [
    { "name": "icon-color-system-ai_1", "font_class": "icon-color-system-ai_1" },
    { "name": "icon-color-system-ai_2", "font_class": "icon-color-system-ai_2" },
    { "name": "icon-color-system-ai_3", "font_class": "icon-color-system-ai_3" },
    { "name": "icon-color-system-ai_message", "font_class": "icon-color-system-ai_message" },
    { "name": "icon-color-system-assistant", "font_class": "icon-color-system-assistant" },
    { "name": "icon-color-system-clean_text", "font_class": "icon-color-system-clean_text" },
    { "name": "icon-color-system-cloud", "font_class": "icon-color-system-cloud" },
    { "name": "icon-color-system-data", "font_class": "icon-color-system-data" },
    { "name": "icon-color-system-dataset", "font_class": "icon-color-system-dataset" },
    { "name": "icon-color-system-dataset_2", "font_class": "icon-color-system-dataset_2" },
    { "name": "icon-color-system-enhance_colors", "font_class": "icon-color-system-enhance_colors" },
    { "name": "icon-color-system-enlarge", "font_class": "icon-color-system-enlarge" },
    { "name": "icon-color-system-enlarge_image", "font_class": "icon-color-system-enlarge_image" },
    { "name": "icon-color-system-finetune", "font_class": "icon-color-system-finetune" },
    { "name": "icon-color-system-generate_document", "font_class": "icon-color-system-generate_document" },
    { "name": "icon-color-system-generate_image_1", "font_class": "icon-color-system-generate_image_1" },
    { "name": "icon-color-system-generate_image_2", "font_class": "icon-color-system-generate_image_2" },
    { "name": "icon-color-system-generate_photo", "font_class": "icon-color-system-generate_photo" },
    { "name": "icon-color-system-generate_text", "font_class": "icon-color-system-generate_text" },
    { "name": "icon-color-system-generate_text_2", "font_class": "icon-color-system-generate_text_2" },
    { "name": "icon-color-system-improve_text", "font_class": "icon-color-system-improve_text" },
    { "name": "icon-color-system-prompt", "font_class": "icon-color-system-prompt" },
    { "name": "icon-color-system-remove_background", "font_class": "icon-color-system-remove_background" },
    { "name": "icon-color-system-search", "font_class": "icon-color-system-search" },
    { "name": "icon-color-system-select", "font_class": "icon-color-system-select" },
    { "name": "icon-color-system-select_2", "font_class": "icon-color-system-select_2" },
    { "name": "icon-color-system-shrink_image", "font_class": "icon-color-system-shrink_image" },
    { "name": "icon-color-system-token", "font_class": "icon-color-system-token" },
    { "name": "icon-color-system-token_2", "font_class": "icon-color-system-token_2" }
  ]
}
